jack-stubs/METADATA.toml
jack-stubs/__init__.pyi
jack-stubs/py.typed
types_jack_client-0.5.10.20250809.dist-info/licenses/LICENSE
types_jack_client-0.5.10.20250809.dist-info/METADATA
types_jack_client-0.5.10.20250809.dist-info/WHEEL
types_jack_client-0.5.10.20250809.dist-info/top_level.txt
types_jack_client-0.5.10.20250809.dist-info/RECORD
